crlibm.pyd
interval/LICENSE
interval/__init__.py
interval/fpu.py
interval/imath.py
pyinterval-1.0.0.dist-info/DESCRIPTION.rst
pyinterval-1.0.0.dist-info/METADATA
pyinterval-1.0.0.dist-info/RECORD
pyinterval-1.0.0.dist-info/WHEEL
pyinterval-1.0.0.dist-info/metadata.json
pyinterval-1.0.0.dist-info/top_level.txt
