Metadata-Version: 2.0
Name: pyinterval
Version: 1.0.0
Summary: Interval arithmetic in Python
Home-page: https://github.com/taschini/pyinterval
Author: Stefano Taschini
Author-email: taschini@gmail.com
License: UNKNOWN
Platform: UNKNOWN
Classifier: Development Status :: 4 - Beta
Classifier: License :: OSI Approved :: BSD License
Classifier: Operating System :: MacOS :: MacOS X
Classifier: Operating System :: Microsoft :: Windows
Classifier: Operating System :: POSIX :: Linux
Classifier: Programming Language :: C
Classifier: Programming Language :: Python
Classifier: Topic :: Scientific/Engineering :: Mathematics
